CHANGELOG.txt
LICENSE
MANIFEST.in
README.txt
__init__.py
requirements.txt
setup.py
test_functions.py
PyChrom.egg-info/PKG-INFO
PyChrom.egg-info/SOURCES.txt
PyChrom.egg-info/dependency_links.txt
PyChrom.egg-info/requires.txt
PyChrom.egg-info/top_level.txt
pychrom/__init__.py
pychrom/src/__init__.py
pychrom/src/pychrom.py
tests/conftest.py