Metadata-Version: 2.1
Name: PyChrom
Version: 0.0.6
Summary: Module to provide tools to process and analyse chromatographic data from different sources such as UPLC, LCMS, GCMS, etc.
Home-page: https://github.com/rdgsnm/PyChrom
Author: Rodrigo Silva Nascimento Mancini
Author-email: rdgsnm@gmail.com
License: MIT
Keywords: chromatography,chemometrics,data preprocessing
Classifier: Development Status :: 3 - Alpha
Classifier: Intended Audience :: Science/Research
Classifier: Operating System :: Microsoft :: Windows :: Windows 11
Classifier: License :: OSI Approved :: MIT License
Classifier: Natural Language :: English
Classifier: Programming Language :: Python :: 3.10
Classifier: Topic :: Scientific/Engineering :: Chemistry
License-File: LICENSE
